setup.py
dfs/__init__.py
dfs/models.py
dfs/scaffold.py
dfs/settings.py
dfs/sofa.py
dfs/tests.py
dfs/management/__init__.py
dfs/management/commands/__init__.py
dfs/management/commands/formscaffold.py
django_form_scaffold.egg-info/PKG-INFO
django_form_scaffold.egg-info/SOURCES.txt
django_form_scaffold.egg-info/dependency_links.txt
django_form_scaffold.egg-info/not-zip-safe
django_form_scaffold.egg-info/top_level.txt