Metadata-Version: 1.0
Name: django-form-scaffold
Version: 1.1.0
Summary: Helper functions for generating templated markup of Django forms
Home-page: http://github.com/1stvamp/django-form-scaffold
Author: Wes Mason
Author-email: wes[at]1stvamp[dot]org
License: Apache License 2.0
Platform: UNKNOWN
Classifier: Framework :: Django
Classifier: Intended Audience :: Developers
Classifier: Intended Audience :: System Administrators
Classifier: Operating System :: OS Independent
Classifier: Topic :: Software Development
